cytounet/__init__.py
cytounet/__main__.py
cytounet/augmentation.py
cytounet/data.py
cytounet/model.py
cytounet/post_model.py
cytounet/version.py
cytounet-0.2.2.dist-info/LICENSE
cytounet-0.2.2.dist-info/METADATA
cytounet-0.2.2.dist-info/WHEEL
cytounet-0.2.2.dist-info/top_level.txt
cytounet-0.2.2.dist-info/RECORD
