Metadata-Version: 2.1
Name: cytounet
Version: 0.2.2
Summary: Deep Learning based Cell Segmentation
Home-page: http://www.github.com/Nelson-Gon/cytounet
Author: Nelson Gonzabato
Author-email: gonzabato@hotmail.com
License: MIT
Download-URL: https://github.com/Nelson-Gon/cytounet/
Keywords: keras tensorflow images image-analysis deep-learning biology
Platform: UNKNOWN
Requires-Python: >=3.6
